gecommon/__init__.py
gecommon/cached_errant.py
gecommon/cached_errant_test.py
gecommon/parallel.py
gecommon/parallel_test.py
gecommon/py.typed
gecommon/utils.py
gecommon/utils_test.py
gecommon/cli/m2_to_raw.py
gecommon-0.2.0.dist-info/METADATA
gecommon-0.2.0.dist-info/WHEEL
gecommon-0.2.0.dist-info/entry_points.txt
gecommon-0.2.0.dist-info/licenses/LICENSE
gecommon-0.2.0.dist-info/RECORD
