Metadata-Version: 2.4
Name: gecommon
Version: 0.2.0
Summary: A common toolkit for Grammatical Error Correction
Author: gotuiyan
License-File: LICENSE
Requires-Python: >=3.11.0
Requires-Dist: errant>=3.0.0
